treegenerator/__init__.py
treegenerator/treegenerator.py
treegenerator-1.0.1.dist-info/METADATA
treegenerator-1.0.1.dist-info/WHEEL
treegenerator-1.0.1.dist-info/licenses/LICENSE.txt
treegenerator-1.0.1.dist-info/RECORD
