Metadata-Version: 2.1
Name: treegenerator
Version: 1.0.1
Summary: Generate a recursive tree diagram given a starting directory or a list of URIs.
Project-URL: Homepage, https://github.com/matt-manes/treegenerator
Project-URL: Documentation, https://github.com/matt-manes/treegenerator/tree/main/docs
Project-URL: Source code, https://github.com/matt-manes/treegenerator/tree/main/src/treegenerator
Author: Matt Manes
License-File: LICENSE.txt
Keywords: directory,tree,visualization
Classifier: License :: OSI Approved :: MIT License
Classifier: Operating System :: OS Independent
Classifier: Programming Language :: Python :: 3
Requires-Python: >=3.10
Requires-Dist: printbuddies
Requires-Dist: pytest
